streamsync/__init__.py
streamsync/app_runner.py
streamsync/app_templates/default/main.py
streamsync/app_templates/default/static/README.md
streamsync/app_templates/default/static/favicon.png
streamsync/app_templates/default/ui.json
streamsync/app_templates/hello/Dockerfile
streamsync/app_templates/hello/assets/main_df.csv
streamsync/app_templates/hello/assets/story.txt
streamsync/app_templates/hello/main.py
streamsync/app_templates/hello/requirements.txt
streamsync/app_templates/hello/static/README.md
streamsync/app_templates/hello/static/favicon.png
streamsync/app_templates/hello/static/neon_feathers.pdf
streamsync/app_templates/hello/static/pigeon1.jpg
streamsync/app_templates/hello/test_app.py
streamsync/app_templates/hello/ui.json
streamsync/command_line.py
streamsync/core.py
streamsync/core_ui.py
streamsync/mypy.ini
streamsync/py.typed
streamsync/serve.py
streamsync/ss_types.py
streamsync/static/assets/Arrow.dom-C52_vrWm.js
streamsync/static/assets/BuilderApp-Co-xyrd-.js
streamsync/static/assets/BuilderApp-Fzhw8njh.css
streamsync/static/assets/ComponentRenderer-DCaUmBUC.css
streamsync/static/assets/ComponentRenderer-DR8XBO3z.js
streamsync/static/assets/Inter-Regular-CKDp9E3C.woff2
streamsync/static/assets/Inter-Regular-CKX1N0ak.ttf
streamsync/static/assets/abap-D8nrxEjS.js
streamsync/static/assets/apex-BrXDlLUW.js
streamsync/static/assets/azcli-CElzELwZ.js
streamsync/static/assets/bat-CUsyEhik.js
streamsync/static/assets/bicep-BtxyJn6H.js
streamsync/static/assets/cameligo-ClBCoF8h.js
streamsync/static/assets/clojure-B9TqLHAk.js
streamsync/static/assets/codicon-BA2IlpFX.ttf
streamsync/static/assets/coffee-DYsfeylR.js
streamsync/static/assets/cpp-VVGvvgir.js
streamsync/static/assets/csharp-Z6z2stHy.js
streamsync/static/assets/csp-DgZoLDI1.js
streamsync/static/assets/css-KqQ96-gC.js
streamsync/static/assets/css.worker-DvNUQFd1.js
streamsync/static/assets/cssMode-DtVHD6mi.js
streamsync/static/assets/cypher-CYoSlgTu.js
streamsync/static/assets/dart-BGDl7St1.js
streamsync-0.5.0.dist-info/LICENSE.txt
streamsync-0.5.0.dist-info/METADATA
streamsync-0.5.0.dist-info/WHEEL
streamsync-0.5.0.dist-info/entry_points.txt
streamsync-0.5.0.dist-info/RECORD
