Metadata-Version: 2.1
Name: streamsync
Version: 0.5.0
Summary: Streamsync helps you create performant data apps, via Python code and its built-in visual UI editor.
Home-page: https://www.streamsync.cloud
License: Apache 2.0
Keywords: data apps,gui,ui
Author: Ramiro Medina
Author-email: ramiro.a.medina@gmail.com
Requires-Python: >=3.9.2,<4.0
Classifier: Development Status :: 4 - Beta
Classifier: License :: Other/Proprietary License
Classifier: Programming Language :: Python :: 3
Classifier: Programming Language :: Python :: 3.10
Classifier: Programming Language :: Python :: 3.11
Classifier: Programming Language :: Python :: 3.12
Classifier: Programming Language :: Python :: 3.9
Provides-Extra: ds
Requires-Dist: fastapi (>=0.89.1,<1)
Requires-Dist: pandas (>=2.2.0,<3) ; extra == "ds"
Requires-Dist: plotly (>=5.18.0,<6) ; extra == "ds"
Requires-Dist: pyarrow (>=15.0.0,<16.0.0) ; extra == "ds"
Requires-Dist: pydantic (>=2.6.0,<3)
Requires-Dist: uvicorn (>=0.20.0,<1)
Requires-Dist: watchdog (>=3.0.0,<4)
Requires-Dist: websockets (>=12,<13)
Project-URL: Documentation, https://www.streamsync.cloud/getting-started.html
Project-URL: Repository, https://www.github.com/streamsync-cloud/streamsync
